numword_georgia/__about__.py
numword_georgia/__init__.py
numword_georgia/translators.py
numword_georgia-0.3.3.dist-info/METADATA
numword_georgia-0.3.3.dist-info/WHEEL
numword_georgia-0.3.3.dist-info/licenses/LICENSE
numword_georgia-0.3.3.dist-info/RECORD
