Metadata-Version: 2.1
Name: numword-georgia
Version: 0.3.3
Summary: Convert numbers to words in Georgian
Project-URL: Documentation, https://github.com/awnion/numword-georgia/#readme
Project-URL: Homepage, https://github.com/awnion/numword-georgia
Project-URL: Issues, https://github.com/awnion/numword-georgia/issues
Project-URL: Repository, https://github.com/awnion/numword-georgia
Project-URL: Source, https://github.com/awnion/numword-georgia
Author-email: Sergei Blinov <blinovsv@gmail.com>
License-Expression: MIT
License-File: LICENSE
Keywords: georgia,numbers,numword
Classifier: Development Status :: 4 - Beta
Classifier: Programming Language :: Python
Classifier: Programming Language :: Python :: 3.8
Classifier: Programming Language :: Python :: 3.9
Classifier: Programming Language :: Python :: 3.10
Classifier: Programming Language :: Python :: 3.11
Classifier: Programming Language :: Python :: 3.12
Classifier: Programming Language :: Python :: Implementation :: CPython
Classifier: Programming Language :: Python :: Implementation :: PyPy
Classifier: Topic :: Software Development :: Libraries :: Python Modules
Requires-Python: >=3.8
